abadge.py
abadge-2.1.1.dist-info/METADATA
abadge-2.1.1.dist-info/RECORD
abadge-2.1.1.dist-info/WHEEL
abadge-2.1.1.dist-info/top_level.txt
