Metadata-Version: 2.1
Name: abadge
Version: 2.1.1
Summary: Generate badges/shields with pure HTML/CSS.
Home-page: https://github.com/Gustra/abadge
Author: Gunnar Strand
Author-email: Gurra.Strand@gmail.com
License: UNKNOWN
Platform: UNKNOWN
